odoo8_addon_base_continent-8.0.1.0.1.99.dev12-py2.7-nspkg.pth
odoo8_addon_base_continent-8.0.1.0.1.99.dev12.dist-info/DESCRIPTION.rst
odoo8_addon_base_continent-8.0.1.0.1.99.dev12.dist-info/METADATA
odoo8_addon_base_continent-8.0.1.0.1.99.dev12.dist-info/RECORD
odoo8_addon_base_continent-8.0.1.0.1.99.dev12.dist-info/WHEEL
odoo8_addon_base_continent-8.0.1.0.1.99.dev12.dist-info/metadata.json
odoo8_addon_base_continent-8.0.1.0.1.99.dev12.dist-info/namespace_packages.txt
odoo8_addon_base_continent-8.0.1.0.1.99.dev12.dist-info/top_level.txt
odoo_addons/base_continent/README.rst
odoo_addons/base_continent/__init__.py
odoo_addons/base_continent/__openerp__.py
odoo_addons/base_continent/data/continent_data.xml
odoo_addons/base_continent/data/country_data.xml
odoo_addons/base_continent/i18n/base_continent.pot
odoo_addons/base_continent/i18n/de.po
odoo_addons/base_continent/i18n/es.po
odoo_addons/base_continent/i18n/eu.po
odoo_addons/base_continent/i18n/fi.po
odoo_addons/base_continent/i18n/fr.po
odoo_addons/base_continent/i18n/it.po
odoo_addons/base_continent/i18n/nl.po
odoo_addons/base_continent/i18n/pt_BR.po
odoo_addons/base_continent/i18n/sl.po
odoo_addons/base_continent/models/__init__.py
odoo_addons/base_continent/models/base_continent.py
odoo_addons/base_continent/models/country.py
odoo_addons/base_continent/models/partner.py
odoo_addons/base_continent/security/ir.model.access.csv
odoo_addons/base_continent/static/description/icon.png
odoo_addons/base_continent/views/continent.xml
odoo_addons/base_continent/views/country.xml
odoo_addons/base_continent/views/partner.xml
